<Properties StartupConfiguration="{030B23AD-ED6E-4A24-07CF-18AFE9D5A6D6}|">
  <MonoDevelop.Ide.Workbench ActiveDocument="Assets/Scripts/Data &amp; Models/DatabaseTest.cs">
    <Files>
      <File FileName="Assets/Scripts/Data &amp; Models/BallObject.cs" Line="6" Column="24" IsPinned="True" />
      <File FileName="Assets/Scripts/Data &amp; Models/BallConfigurations.cs" Line="8" Column="17" IsPinned="True" />
      <File FileName="Assets/Scripts/Data &amp; Models/SqliteHelper.cs" />
      <File FileName="Assets/Scripts/Data &amp; Models/DatabaseTest.cs" Line="10" Column="12" />
    </Files>
    <Pads>
      <Pad Id="ProjectPad">
        <State name="__root__">
          <Node name="FitMi Plus Game" expanded="True">
            <Node name="Assets" expanded="True">
              <Node name="Editor" expanded="True" />
              <Node name="Plugins" expanded="True">
                <Node name="BluetoothLE" expanded="True">
                  <Node name="Android" expanded="True" />
                </Node>
              </Node>
              <Node name="Resources" expanded="True" />
              <Node name="Scripts" expanded="True">
                <Node name="Controllers" expanded="True" />
                <Node name="Data &amp; Models" expanded="True">
                  <Node name="DatabaseTest.cs" selected="True" />
                </Node>
                <Node name="Managers" expanded="True" />
                <Node name="Motion &amp; Physics" expanded="True" />
                <Node name="Utils" expanded="True" />
                <Node name="Visuals" expanded="True" />
              </Node>
            </Node>
          </Node>
        </State>
      </Pad>
    </Pads>
  </MonoDevelop.Ide.Workbench>
  <MonoDevelop.Ide.DebuggingService.PinnedWatches />
  <MonoDevelop.Ide.Workspace ActiveConfiguration="Debug" />
  <MonoDevelop.Ide.ItemProperties.Assembly-CSharp PreferredExecutionTarget="4f17788d-ae53-4437-abd4-1130c611996d" />
  <MonoDevelop.Ide.DebuggingService.Breakpoints>
    <BreakpointStore />
  </MonoDevelop.Ide.DebuggingService.Breakpoints>
  <MultiItemStartupConfigurations />
</Properties>